rss_parser/Output_functions.py
rss_parser/rss_parser.py
FinalTaskRssParser-1.0.dist-info/METADATA
FinalTaskRssParser-1.0.dist-info/WHEEL
FinalTaskRssParser-1.0.dist-info/top_level.txt
FinalTaskRssParser-1.0.dist-info/RECORD
